ClassificationModels/CNN.py
ClassificationModels/CNN_T.py
ClassificationModels/DecisionTree.py
ClassificationModels/LSTM.py
ClassificationModels/LSTM_T.py
ClassificationModels/ResNet.py
ClassificationModels/__init__.py
ClassificationModels/utils.py
TSInterpret/__init__.py
TSInterpret/__version__.py
TSInterpret/constants.py
TSInterpret/InterpretabilityModels/FeatureAttribution.py
TSInterpret/InterpretabilityModels/InstanceBase.py
TSInterpret/InterpretabilityModels/InterpretabilityBase.py
TSInterpret/InterpretabilityModels/__init__.py
TSInterpret/InterpretabilityModels/GradCam/GradCam_1D.py
TSInterpret/InterpretabilityModels/GradCam/__init__.py
TSInterpret/InterpretabilityModels/Saliency/SaliencyMethods_PTY.py
TSInterpret/InterpretabilityModels/Saliency/SaliencyMethods_TF.py
TSInterpret/InterpretabilityModels/Saliency/Saliency_Base.py
TSInterpret/InterpretabilityModels/Saliency/TSR.py
TSInterpret/InterpretabilityModels/Saliency/__init__.py
TSInterpret/InterpretabilityModels/counterfactual/CF.py
TSInterpret/InterpretabilityModels/counterfactual/COMTECF.py
TSInterpret/InterpretabilityModels/counterfactual/NativeGuideCF.py
TSInterpret/InterpretabilityModels/counterfactual/SETSCF.py
TSInterpret/InterpretabilityModels/counterfactual/TSEvoCF.py
TSInterpret/InterpretabilityModels/counterfactual/__init__.py
TSInterpret/InterpretabilityModels/counterfactual/COMTE/Optimization.py
TSInterpret/InterpretabilityModels/counterfactual/COMTE/Optimization_helpers.py
TSInterpret/InterpretabilityModels/counterfactual/COMTE/Problem.py
TSInterpret/InterpretabilityModels/counterfactual/COMTE/__init__.py
TSInterpret/InterpretabilityModels/counterfactual/SETS/ContractedST.py
TSInterpret/InterpretabilityModels/counterfactual/SETS/__init__.py
TSInterpret/InterpretabilityModels/counterfactual/SETS/sets.py
TSInterpret/InterpretabilityModels/counterfactual/SETS/utils.py
TSInterpret/InterpretabilityModels/counterfactual/TSEvo/Evo.py
TSInterpret-0.4.7.dist-info/LICENSE
TSInterpret-0.4.7.dist-info/METADATA
TSInterpret-0.4.7.dist-info/WHEEL
TSInterpret-0.4.7.dist-info/top_level.txt
TSInterpret-0.4.7.dist-info/RECORD
