Metadata-Version: 2.1
Name: TSInterpret
Version: 0.4.7
Summary: todo
Home-page: https://ipe-wim-gitlab.fzi.de/hoellig/interpretabilitytimeseries
Author: Jacqueline Hoellig
Author-email: hoellig@fzi.de
License: BSD-3
Classifier: License :: OSI Approved :: BSD License
Classifier: Programming Language :: Python
Classifier: Programming Language :: Python :: 3
Classifier: Programming Language :: Python :: 3.7
Classifier: Programming Language :: Python :: 3.8
Classifier: Programming Language :: Python :: 3.9
Classifier: Programming Language :: Python :: 3.10
Classifier: Programming Language :: Python :: Implementation :: CPython
Classifier: Programming Language :: Python :: Implementation :: PyPy
Requires-Python: >=3.6.0
License-File: LICENSE
Requires-Dist: scikit-learn==1.3.0
Requires-Dist: torch<3.0,>=1.13.0
Requires-Dist: pandas<=3.0.0
Requires-Dist: numpy<2.0,>=1.21.6
Requires-Dist: tqdm<4.66.0,>=4.61.2
Requires-Dist: h5py
Requires-Dist: joblib<2.0,>=1.0.1
Requires-Dist: Markdown<4.0,==3.3.4
Requires-Dist: matplotlib<4.0,>=3.3.4
Requires-Dist: partd==1.2.0
Requires-Dist: pytz>=2021.3
Requires-Dist: shap<1.0,>=0.39.0
Requires-Dist: tensorflow>=2.9.1
Requires-Dist: keras>=2.9.0
Requires-Dist: tsfresh<1.0,>=0.18.0
Requires-Dist: tslearn<1.0,>=0.5.2
Requires-Dist: seaborn<1.0,>=0.11.2
Requires-Dist: scikit_optimize<1.0,>=0.9.0
Requires-Dist: torchcam<1.0,>=0.3.1
Requires-Dist: tf_explain<1.0,>=0.3.1
Requires-Dist: opencv-python==4.6.0.66
Requires-Dist: captum<1.0,>=0.5.0
Requires-Dist: pyts<1.0,>=0.12.0
Requires-Dist: deprecated==1.2.13
Requires-Dist: pymop
Requires-Dist: deap
Requires-Dist: wheel
Requires-Dist: sktime
Provides-Extra: dev
Requires-Dist: scikit-learn==1.3.0; extra == "dev"
Requires-Dist: torch<3.0,>=1.13.0; extra == "dev"
Requires-Dist: pandas<=3.0.0; extra == "dev"
Requires-Dist: numpy<2.0,>=1.21.6; extra == "dev"
Requires-Dist: tqdm<4.66.0,>=4.61.2; extra == "dev"
Requires-Dist: h5py; extra == "dev"
Requires-Dist: joblib<2.0,>=1.0.1; extra == "dev"
Requires-Dist: Markdown<4.0,==3.3.4; extra == "dev"
Requires-Dist: matplotlib<4.0,>=3.3.4; extra == "dev"
Requires-Dist: partd==1.2.0; extra == "dev"
Requires-Dist: pytz>=2021.3; extra == "dev"
Requires-Dist: shap<1.0,>=0.39.0; extra == "dev"
Requires-Dist: tensorflow>=2.9.1; extra == "dev"
Requires-Dist: keras>=2.9.0; extra == "dev"
Requires-Dist: tsfresh<1.0,>=0.18.0; extra == "dev"
Requires-Dist: tslearn<1.0,>=0.5.2; extra == "dev"
Requires-Dist: seaborn<1.0,>=0.11.2; extra == "dev"
Requires-Dist: scikit_optimize<1.0,>=0.9.0; extra == "dev"
Requires-Dist: torchcam<1.0,>=0.3.1; extra == "dev"
Requires-Dist: tf_explain<1.0,>=0.3.1; extra == "dev"
Requires-Dist: opencv-python==4.6.0.66; extra == "dev"
Requires-Dist: captum<1.0,>=0.5.0; extra == "dev"
Requires-Dist: pyts<1.0,>=0.12.0; extra == "dev"
Requires-Dist: deprecated==1.2.13; extra == "dev"
Requires-Dist: pymop; extra == "dev"
Requires-Dist: deap; extra == "dev"
Requires-Dist: wheel; extra == "dev"
Requires-Dist: sktime; extra == "dev"
Requires-Dist: flake8<6.0,>=5.0.4; extra == "dev"
Requires-Dist: isort==5.9.3; extra == "dev"
Requires-Dist: mypy<1.0,>=0.761; extra == "dev"
Requires-Dist: pre-commit<3.0,>=2.9.2; extra == "dev"
Requires-Dist: pytest>=6.2.5; extra == "dev"
Requires-Dist: pytest-cov<3.0,>=2.6.1; extra == "dev"
Requires-Dist: pyupgrade<4.0,>=3.2.0; extra == "dev"
Provides-Extra: test
Requires-Dist: scikit-learn==1.3.0; extra == "test"
Requires-Dist: torch<3.0,>=1.13.0; extra == "test"
Requires-Dist: pandas<=3.0.0; extra == "test"
Requires-Dist: numpy<2.0,>=1.21.6; extra == "test"
Requires-Dist: tqdm<4.66.0,>=4.61.2; extra == "test"
Requires-Dist: h5py; extra == "test"
Requires-Dist: joblib<2.0,>=1.0.1; extra == "test"
Requires-Dist: Markdown<4.0,==3.3.4; extra == "test"
Requires-Dist: matplotlib<4.0,>=3.3.4; extra == "test"
Requires-Dist: partd==1.2.0; extra == "test"
Requires-Dist: pytz>=2021.3; extra == "test"
Requires-Dist: shap<1.0,>=0.39.0; extra == "test"
Requires-Dist: tensorflow>=2.9.1; extra == "test"
Requires-Dist: keras>=2.9.0; extra == "test"
Requires-Dist: tsfresh<1.0,>=0.18.0; extra == "test"
Requires-Dist: tslearn<1.0,>=0.5.2; extra == "test"
Requires-Dist: seaborn<1.0,>=0.11.2; extra == "test"
Requires-Dist: scikit_optimize<1.0,>=0.9.0; extra == "test"
Requires-Dist: torchcam<1.0,>=0.3.1; extra == "test"
Requires-Dist: tf_explain<1.0,>=0.3.1; extra == "test"
Requires-Dist: opencv-python==4.6.0.66; extra == "test"
Requires-Dist: captum<1.0,>=0.5.0; extra == "test"
Requires-Dist: pyts<1.0,>=0.12.0; extra == "test"
Requires-Dist: deprecated==1.2.13; extra == "test"
Requires-Dist: pymop; extra == "test"
Requires-Dist: deap; extra == "test"
Requires-Dist: wheel; extra == "test"
Requires-Dist: sktime; extra == "test"
Requires-Dist: flake8<6.0,>=5.0.4; extra == "test"
Requires-Dist: isort==5.9.3; extra == "test"
Requires-Dist: mypy<1.0,>=0.761; extra == "test"
Requires-Dist: pre-commit<3.0,>=2.9.2; extra == "test"
Requires-Dist: pytest>=6.2.5; extra == "test"
Requires-Dist: pytest-cov<3.0,>=2.6.1; extra == "test"
Requires-Dist: pyupgrade<4.0,>=3.2.0; extra == "test"
Provides-Extra: docs
Requires-Dist: flask<3.0,>=2.0.2; extra == "docs"
Requires-Dist: ipykernel<7.0,>=6.9.0; extra == "docs"
Requires-Dist: mike<1.0,>=0.5.3; extra == "docs"
Requires-Dist: mkdocs<2.0,>=1.2.3; extra == "docs"
Requires-Dist: mkdocs-awesome-pages-plugin<3.0,>=2.7.0; extra == "docs"
Requires-Dist: mkdocs-gen-files<1.0,>=0.3.5; extra == "docs"
Requires-Dist: mkdocs-literate-nav<1.0,>=0.4.1; extra == "docs"
Requires-Dist: mkdocs-material<9.0,>=8.1.11; extra == "docs"
Requires-Dist: mkdocstrings[python]<1.0,>=0.19.0; extra == "docs"
Requires-Dist: pytkdocs[numpy-style]<1.0,>=0.5.0; extra == "docs"
Requires-Dist: ipython_genutils<1.0,>=0.1.0; extra == "docs"
Requires-Dist: mkdocs-jupyter<1.0,>=0.20.0; extra == "docs"
Requires-Dist: mkdocs-bibtex==2.8.1; extra == "docs"
Requires-Dist: nbconvert==6.4.2; extra == "docs"
Requires-Dist: numpydoc==1.2; extra == "docs"
Requires-Dist: spacy==3.2.2; extra == "docs"
Requires-Dist: jinja2==3.0.3; extra == "docs"
Provides-Extra: all
Requires-Dist: scikit-learn==1.3.0; extra == "all"
Requires-Dist: torch<3.0,>=1.13.0; extra == "all"
Requires-Dist: pandas<=3.0.0; extra == "all"
Requires-Dist: numpy<2.0,>=1.21.6; extra == "all"
Requires-Dist: tqdm<4.66.0,>=4.61.2; extra == "all"
Requires-Dist: h5py; extra == "all"
Requires-Dist: joblib<2.0,>=1.0.1; extra == "all"
Requires-Dist: Markdown<4.0,==3.3.4; extra == "all"
Requires-Dist: matplotlib<4.0,>=3.3.4; extra == "all"
Requires-Dist: partd==1.2.0; extra == "all"
Requires-Dist: pytz>=2021.3; extra == "all"
Requires-Dist: shap<1.0,>=0.39.0; extra == "all"
Requires-Dist: tensorflow>=2.9.1; extra == "all"
Requires-Dist: keras>=2.9.0; extra == "all"
Requires-Dist: tsfresh<1.0,>=0.18.0; extra == "all"
Requires-Dist: tslearn<1.0,>=0.5.2; extra == "all"
Requires-Dist: seaborn<1.0,>=0.11.2; extra == "all"
Requires-Dist: scikit_optimize<1.0,>=0.9.0; extra == "all"
Requires-Dist: torchcam<1.0,>=0.3.1; extra == "all"
Requires-Dist: tf_explain<1.0,>=0.3.1; extra == "all"
Requires-Dist: opencv-python==4.6.0.66; extra == "all"
Requires-Dist: captum<1.0,>=0.5.0; extra == "all"
Requires-Dist: pyts<1.0,>=0.12.0; extra == "all"
Requires-Dist: deprecated==1.2.13; extra == "all"
Requires-Dist: pymop; extra == "all"
Requires-Dist: deap; extra == "all"
Requires-Dist: wheel; extra == "all"
Requires-Dist: sktime; extra == "all"
Requires-Dist: flake8<6.0,>=5.0.4; extra == "all"
Requires-Dist: isort==5.9.3; extra == "all"
Requires-Dist: mypy<1.0,>=0.761; extra == "all"
Requires-Dist: pre-commit<3.0,>=2.9.2; extra == "all"
Requires-Dist: pytest>=6.2.5; extra == "all"
Requires-Dist: pytest-cov<3.0,>=2.6.1; extra == "all"
Requires-Dist: pyupgrade<4.0,>=3.2.0; extra == "all"
Requires-Dist: flask<3.0,>=2.0.2; extra == "all"
Requires-Dist: ipykernel<7.0,>=6.9.0; extra == "all"
Requires-Dist: mike<1.0,>=0.5.3; extra == "all"
Requires-Dist: mkdocs<2.0,>=1.2.3; extra == "all"
Requires-Dist: mkdocs-awesome-pages-plugin<3.0,>=2.7.0; extra == "all"
Requires-Dist: mkdocs-gen-files<1.0,>=0.3.5; extra == "all"
Requires-Dist: mkdocs-literate-nav<1.0,>=0.4.1; extra == "all"
Requires-Dist: mkdocs-material<9.0,>=8.1.11; extra == "all"
Requires-Dist: mkdocstrings[python]<1.0,>=0.19.0; extra == "all"
Requires-Dist: pytkdocs[numpy-style]<1.0,>=0.5.0; extra == "all"
Requires-Dist: ipython_genutils<1.0,>=0.1.0; extra == "all"
Requires-Dist: mkdocs-jupyter<1.0,>=0.20.0; extra == "all"
Requires-Dist: mkdocs-bibtex==2.8.1; extra == "all"
Requires-Dist: nbconvert==6.4.2; extra == "all"
Requires-Dist: numpydoc==1.2; extra == "all"
Requires-Dist: spacy==3.2.2; extra == "all"
Requires-Dist: jinja2==3.0.3; extra == "all"
Requires-Dist: dataclasses; python_version == "3.8"
